{
  "title": "Ценность фигур",
  "categories": [
    {
      "name": "Ценость фигур",
      "questions": [
        {
          "value": 100,
          "question": "Сколько стоит конь?",
          "answer": "3 пешки",
          "fen": "8/8/8/8/3N4/8/8/8 w - - 0 1"
        },
        {
          "value": 200,
          "question": "Сколько стоит ладья?",
          "answer": "5 пешек",
          "fen": "8/8/8/8/3R4/8/8/8 w - - 0 1"
        },
        {
          "value": 300,
          "question": "Сколько стоит ферзь?",
          "answer": "9 пешек",
          "fen": "8/8/8/8/3Q4/8/8/8 w - - 0 1"
        },
        {
          "value": 400,
          "question": "Сколько стоит король?",
          "answer": "100 пешек",
          "fen": "8/8/8/8/3K4/8/8/8 w - - 0 1"
        }
      ]
    },
    {
      "name": "У кого преимущество?",
      "questions": [
        {
          "value": 100,
          "question": "У кого преимущество?",
          "answer": "У белых",
          "fen": "8/3r4/2k5/8/8/Q7/K7/8 w - - 0 1"
        },
        {
          "value": 200,
          "question": "У кого преимущество?",
          "answer": "У черных",
          "fen": "8/8/2kr4/3q4/8/5QN1/6K1/8 w - - 0 1"
        },
        {
          "value": 300,
          "question": "У кого преимущество?",
          "answer": "У белых",
          "fen": "8/8/8/2k5/2n1P3/5P1P/4K1P1/8 w - - 0 1"
        },
        {
          "value": 400,
          "question": "У кого преимущество?",
          "answer": "Равная позиция",
          "fen": "3k4/3q4/3nbpp1/1P6/2P1N3/1QKP1P2/4P3/8 w - - 0 1"
        }
      ]
    },
    {
      "name": "Что выгоднее скушать?",
      "questions": [
        {
          "value": 100,
          "question": "Что выгоднее скушать?",
          "answer": "Ферзя",
          "fen": "n4r1k/qB4pp/8/3P4/1P3Q2/7P/3R3K/6R1 b - - 0 1"
        },
        {
          "value": 200,
          "question": "Что выгоднее скушать?",
          "answer": "Ладью",
          "fen": "7r/1pr2k2/1R2p3/3N1p1p/P1P4n/6P1/5P1P/5K2 w - - 0 1"
        },
        {
          "value": 300,
          "question": "Что выгоднее скушать?",
          "answer": "Ладью",
          "fen": "4r3/6k1/1pQP4/p4p2/2P2rp1/1P6/P6P/6bK w - - 0 1"
        },
        {
          "value": 400,
          "question": "Что выгоднее скушать?",
          "answer": "Ферзя",
          "fen": "rn5k/p6p/6p1/2pq4/8/2N1B3/PP3PPb/R6K w - - 0 1"
        }
      ]
    }
  ]
}